LICENSE
README.md
setup.cfg
setup.py
lasertools_pulsepropagate/__init__.py
lasertools_pulsepropagate/propagate.py
lasertools_pulsepropagate.egg-info/PKG-INFO
lasertools_pulsepropagate.egg-info/SOURCES.txt
lasertools_pulsepropagate.egg-info/dependency_links.txt
lasertools_pulsepropagate.egg-info/requires.txt
lasertools_pulsepropagate.egg-info/top_level.txt