Metadata-Version: 2.1
Name: lasertools-pulsepropagate
Version: 0.0.1.1
Summary: A module to handle simple pulse propagation with dispersion and nlo
Home-page: https://github.com/lasertools/lasertools_pulsepropagate
Author: brittonm
Author-email: 68578865+brittonm@users.noreply.github.com
License: GPLv3
Download-URL: https://github.com/lasertools/lasertools_pulsepropagate/archive/refs/tags/v_0_0_1_1.tar.gz
Platform: UNKNOWN
Classifier: Programming Language :: Python :: 3.9
License-File: LICENSE
